{
  "orderId": "2410110029",
  "name": "Umer Khan",
  "phone": "7866786",
  "country": "",
  "email": "mumarkhan383@gmail.com",
  "notes": "sending files...",
  "topic": "hgghfgf",
  "selectedValue": "1",
  "wordCount": "300",
  "level": "undergraduate",
  "paper": "Dissertation",
  "quality": "Standard Quality",
  "deadline": "17 days",
  "subject": "Chemistry",
  "source": "10",
  "format": "Double Spaced",
  "referencing": "Harvard Referencing",
  "pricePerPage": "8",
  "totalPrice": "8",
  "file": [
    {},
    {},
    {}
  ],
  "language": "English (U.K)"
}